inquire/__init__.py
inquire/baml_manager.py
inquire/cli.py
inquire/config.py
inquire/core.py
inquire/exceptions.py
inquire/types.py
inquire_py-0.1.2.dist-info/METADATA
inquire_py-0.1.2.dist-info/WHEEL
inquire_py-0.1.2.dist-info/entry_points.txt
inquire_py-0.1.2.dist-info/licenses/LICENSE
inquire_py-0.1.2.dist-info/RECORD
