Metadata-Version: 2.4
Name: inquire-py
Version: 0.1.2
Summary: Intelligent inquiry with structured results - BAML + Deep Research
Project-URL: Homepage, https://github.com/daviddl9/inquire
Project-URL: Repository, https://github.com/daviddl9/inquire
Project-URL: Issues, https://github.com/daviddl9/inquire/issues
Author-email: David Livingston <ddl.tdh@gmail.com>
License: MIT
License-File: LICENSE
Keywords: ai,baml,llm,research,structured-extraction
Classifier: Development Status :: 3 - Alpha
Classifier: Intended Audience :: Developers
Classifier: License :: OSI Approved :: MIT License
Classifier: Programming Language :: Python :: 3
Classifier: Programming Language :: Python :: 3.11
Classifier: Programming Language :: Python :: 3.12
Classifier: Topic :: Scientific/Engineering :: Artificial Intelligence
Requires-Python: >=3.11
Requires-Dist: baml-py==0.205.0
Requires-Dist: click>=8.0.0
Requires-Dist: httpx>=0.24.0
Requires-Dist: openai>=1.0.0
Requires-Dist: pydantic>=2.0
Requires-Dist: tavily-python>=0.5.0
Provides-Extra: dev
Requires-Dist: mypy>=1.8; extra == 'dev'
Requires-Dist: pytest-asyncio>=0.23; extra == 'dev'
Requires-Dist: pytest-cov>=4.0; extra == 'dev'
Requires-Dist: pytest>=8.0; extra == 'dev'
Requires-Dist: ruff>=0.3; extra == 'dev'
